jhub_remote_user_authenticator/__init__.py
jhub_remote_user_authenticator/remote_user_auth.py
jhub_remote_user_authenticator-0.1.0.dist-info/DESCRIPTION.rst
jhub_remote_user_authenticator-0.1.0.dist-info/METADATA
jhub_remote_user_authenticator-0.1.0.dist-info/RECORD
jhub_remote_user_authenticator-0.1.0.dist-info/WHEEL
jhub_remote_user_authenticator-0.1.0.dist-info/metadata.json
jhub_remote_user_authenticator-0.1.0.dist-info/top_level.txt
