Metadata-Version: 2.0
Name: jhub-remote-user-authenticator
Version: 0.1.0
Summary: REMOTE_USER Authenticator: An Authenticator for Jupyterhub to read user information from HTTP request headers, as when running behind an authenticating proxy.
Home-page: https://github.com/cwaldbieser/jhub_remote_user_authenticator
Author: Carl (https://github.com/cwaldbieser)
Author-email: UNKNOWN
License: GPLv3
Keywords: Interactive,Interpreter,Shell,Web
Platform: Linux
Platform: Mac OS X
Classifier: Intended Audience :: Developers
Classifier: Intended Audience :: System Administrators
Classifier: Intended Audience :: Science/Research
Classifier: License :: OSI Approved :: GNU General Public License v3 (GPLv3)
Classifier: Programming Language :: Python
Classifier: Programming Language :: Python :: 3
Requires-Dist: jupyterhub
